Metadata-Version: 2.1
Name: me_toolbox
Version: 0.0.17
Summary: Mechanical engineering design tools
Home-page: https://github.com/OmriStein/MEtoolbox
Author: Omri Stein
Author-email: omri.stein@gmail.com
Project-URL: Bug Tracker, https://github.com/OmriStein/MEtoolbox/issues
Classifier: Development Status :: 1 - Planning
Classifier: Intended Audience :: Education
Classifier: Topic :: Scientific/Engineering
Classifier: Programming Language :: Python :: 3.9
Classifier: License :: OSI Approved :: MIT License
Classifier: Operating System :: OS Independent
Requires-Python: >=3.9
License-File: LICENSE
Requires-Dist: sympy
Requires-Dist: numpy
Requires-Dist: mpmath
